.bumpversion.cfg
CONTRIBUTING.md
LICENSE
MANIFEST.in
Makefile
README.md
pyproject.toml
setup.py
src/Base.py
src/__init__.py
src/interactive_score_editor.egg-info/PKG-INFO
src/interactive_score_editor.egg-info/SOURCES.txt
src/interactive_score_editor.egg-info/dependency_links.txt
src/interactive_score_editor.egg-info/requires.txt
src/interactive_score_editor.egg-info/top_level.txt
src/tests/test_all.py
temp/TESTING.md