Metadata-Version: 2.1
Name: interactive-score-editor
Version: 0.1.3
Summary: Interactive Score Editor
Author-email: Sadi Gulcelik <sg3790@columbia.edu>
License:                                  Apache License
Project-URL: repository, https://github.com/sadigulcelik/interactive-score-editor
Classifier: Programming Language :: Python :: 3.10
Requires-Python: >=3.7
Provides-Extra: develop
License-File: LICENSE
